{
	"ቀን": [
		"ቀን",
		"ቀንን",
		"ቀንው",
		"ቀንያቸው",
		"ቀንዬ"
	],
	"ሰው": [
		"ሰው",
		"ሰውን",
		"ሰውው",
		"ሰውያቸው",
		"ሰውዬ"
	],
	"ቤት": [
		"ቤት",
		"ቤትን",
		"ቤትው",
		"ቤትያቸው",
		"ቤትዬ"
	],
	"መኪና": [
		"መኪና",
		"መኪናን",
		"መኪናው",
		"መኪናያቸው",
		"መኪናዬ"
	],
	"መንገድ": [
		"መንገድ",
		"መንገድን",
		"መንገድው",
		"መንገድያቸው",
		"መንገድዬ"
	],
	"ችግኝ": [
		"ችግኝ",
		"ችግኝን",
		"ችግኝው",
		"ችግኝያቸው",
		"ችግኝዬ"
	],
	"መፍትሔ": [
		"መፍትሔ",
		"መፍትሔን",
		"መፍትሔው",
		"መፍትሔያቸው",
		"መፍትሔዬ"
	],
	"ትምህርት": [
		"ትምህርት",
		"ትምህርትን",
		"ትምህርትው",
		"ትምህርትያቸው",
		"ትምህርትዬ"
	],
	"መምህር": [
		"መምህር",
		"መምህርን",
		"መምህርው",
		"መምህርያቸው",
		"መምህርዬ"
	],
	"ተማሪ": [
		"ተማሪ",
		"ተማሪን",
		"ተማሪው",
		"ተማሪያቸው",
		"ተማሪዬ"
	],
	"መጽሐፍ": [
		"መጽሐፍ",
		"መጽሐፍን",
		"መጽሐፍው",
		"መጽሐፍያቸው",
		"መጽሐፍዬ"
	],
	"ትምህርትቤት": [
		"ትምህርትቤት",
		"ትምህርትቤትን",
		"ትምህርትቤትው",
		"ትምህርትቤትያቸው",
		"ትምህርትቤትዬ"
	],
	"ዩኒቨርሲቲ": [
		"ዩኒቨርሲቲ",
		"ዩኒቨርሲቲን",
		"ዩኒቨርሲቲው",
		"ዩኒቨርሲቲያቸው",
		"ዩኒቨርሲቲዬ"
	],
	"ስራ": [
		"ስራ",
		"ስራን",
		"ስራው",
		"ስራያቸው",
		"ስራዬ"
	],
	"ጤና": [
		"ጤና",
		"ጤናን",
		"ጤናው",
		"ጤናያቸው",
		"ጤናዬ"
	],
	"ሀብት": [
		"ሀብት",
		"ሀብትን",
		"ሀብትው",
		"ሀብትያቸው",
		"ሀብትዬ"
	],
	"ገንዘብ": [
		"ገንዘብ",
		"ገንዘብን",
		"ገንዘብው",
		"ገንዘብያቸው",
		"ገንዘብዬ"
	],
	"ዋጋ": [
		"ዋጋ",
		"ዋጋን",
		"ዋጋው",
		"ዋጋያቸው",
		"ዋጋዬ"
	],
	"ገበያ": [
		"ገበያ",
		"ገበያን",
		"ገበያው",
		"ገበያያቸው",
		"ገበያዬ"
	],
	"ሱቅ": [
		"ሱቅ",
		"ሱቅን",
		"ሱቅው",
		"ሱቅያቸው",
		"ሱቅዬ"
	],
	"ሆቴል": [
		"ሆቴል",
		"ሆቴልን",
		"ሆቴልው",
		"ሆቴልያቸው",
		"ሆቴልዬ"
	],
	"ሆስፒታል": [
		"ሆስፒታል",
		"ሆስፒታልን",
		"ሆስፒታልው",
		"ሆስፒታልያቸው",
		"ሆስፒታልዬ"
	],
	"መድሀኒት": [
		"መድሀኒት",
		"መድሀኒትን",
		"መድሀኒትው",
		"መድሀኒትያቸው",
		"መድሀኒትዬ"
	],
	"እንጀራ": [
		"እንጀራ",
		"እንጀራን",
		"እንጀራው",
		"እንጀራያቸው",
		"እንጀራዬ"
	],
	"ዳቦ": [
		"ዳቦ",
		"ዳቦን",
		"ዳቦው",
		"ዳቦያቸው",
		"ዳቦዬ"
	],
	"ወጥ": [
		"ወጥ",
		"ወጥን",
		"ወጥው",
		"ወጥያቸው",
		"ወጥዬ"
	],
	"ስጋ": [
		"ስጋ",
		"ስጋን",
		"ስጋው",
		"ስጋያቸው",
		"ስጋዬ"
	],
	"እሳት": [
		"እሳት",
		"እሳትን",
		"እሳትው",
		"እሳትያቸው",
		"እሳትዬ"
	],
	"ዛፍ": [
		"ዛፍ",
		"ዛፍን",
		"ዛፍው",
		"ዛፍያቸው",
		"ዛፍዬ"
	],
	"ተክል": [
		"ተክል",
		"ተክልን",
		"ተክልው",
		"ተክልያቸው",
		"ተክልዬ"
	],
	"አበባ": [
		"አበባ",
		"አበባን",
		"አበባው",
		"አበባያቸው",
		"አበባዬ"
	],
	"ጸሀይ": [
		"ጸሀይ",
		"ጸሀይን",
		"ጸሀይው",
		"ጸሀይያቸው",
		"ጸሀይዬ"
	],
	"ጨረቃ": [
		"ጨረቃ",
		"ጨረቃን",
		"ጨረቃው",
		"ጨረቃያቸው",
		"ጨረቃዬ"
	],
	"ከዋክብት": [
		"ከዋክብት",
		"ከዋክብትን",
		"ከዋክብትው",
		"ከዋክብትያቸው",
		"ከዋክብትዬ"
	],
	"ዝናብ": [
		"ዝናብ",
		"ዝናብን",
		"ዝናብው",
		"ዝናብያቸው",
		"ዝናብዬ"
	],
	"ነፋስ": [
		"ነፋስ",
		"ነፋስን",
		"ነፋስው",
		"ነፋስያቸው",
		"ነፋስዬ"
	],
	"ጭጋግ": [
		"ጭጋግ",
		"ጭጋግን",
		"ጭጋግው",
		"ጭጋግያቸው",
		"ጭጋግዬ"
	],
	"ተራራ": [
		"ተራራ",
		"ተራራን",
		"ተራራው",
		"ተራራያቸው",
		"ተራራዬ"
	],
	"ወንዝ": [
		"ወንዝ",
		"ወንዝን",
		"ወንዝው",
		"ወንዝያቸው",
		"ወንዝዬ"
	],
	"ሀይቅ": [
		"ሀይቅ",
		"ሀይቅን",
		"ሀይቅው",
		"ሀይቅያቸው",
		"ሀይቅዬ"
	],
	"መኝታ": [
		"መኝታ",
		"መኝታን",
		"መኝታው",
		"መኝታያቸው",
		"መኝታዬ"
	],
	"አልጋ": [
		"አልጋ",
		"አልጋን",
		"አልጋው",
		"አልጋያቸው",
		"አልጋዬ"
	],
	"ወንበር": [
		"ወንበር",
		"ወንበርን",
		"ወንበርው",
		"ወንበርያቸው",
		"ወንበርዬ"
	],
	"ጠረጴዛ": [
		"ጠረጴዛ",
		"ጠረጴዛን",
		"ጠረጴዛው",
		"ጠረጴዛያቸው",
		"ጠረጴዛዬ"
	],
	"መስኮት": [
		"መስኮት",
		"መስኮትን",
		"መስኮትው",
		"መስኮትያቸው",
		"መስኮትዬ"
	],
	"ቁልፍ": [
		"ቁልፍ",
		"ቁልፍን",
		"ቁልፍው",
		"ቁልፍያቸው",
		"ቁልፍዬ"
	],
	"መዝጊያ": [
		"መዝጊያ",
		"መዝጊያን",
		"መዝጊያው",
		"መዝጊያያቸው",
		"መዝጊያዬ"
	],
	"ብርሃን": [
		"ብርሃን",
		"ብርሃንን",
		"ብርሃንው",
		"ብርሃንያቸው",
		"ብርሃንዬ"
	],
	"መብራት": [
		"መብራት",
		"መብራትን",
		"መብራትው",
		"መብራትያቸው",
		"መብራትዬ"
	],
	"መቀመጫ": [
		"መቀመጫ",
		"መቀመጫን",
		"መቀመጫው",
		"መቀመጫያቸው",
		"መቀመጫዬ"
	],
	"መዋኛ": [
		"መዋኛ",
		"መዋኛን",
		"መዋኛው",
		"መዋኛያቸው",
		"መዋኛዬ"
	],
	"መክፈቻ": [
		"መክፈቻ",
		"መክፈቻን",
		"መክፈቻው",
		"መክፈቻያቸው",
		"መክፈቻዬ"
	],
	"ጨርቅ": [
		"ጨርቅ",
		"ጨርቅን",
		"ጨርቅው",
		"ጨርቅያቸው",
		"ጨርቅዬ"
	],
	"ልብስ": [
		"ልብስ",
		"ልብስን",
		"ልብስው",
		"ልብስያቸው",
		"ልብስዬ"
	],
	"ጫማ": [
		"ጫማ",
		"ጫማን",
		"ጫማው",
		"ጫማያቸው",
		"ጫማዬ"
	],
	"እግር": [
		"እግር",
		"እግርን",
		"እግርው",
		"እግርያቸው",
		"እግርዬ"
	],
	"እጅ": [
		"እጅ",
		"እጅን",
		"እጅው",
		"እጅያቸው",
		"እጅዬ"
	],
	"ቡና": [
		"ቡና",
		"ቡናን",
		"ቡናው",
		"ቡናያቸው",
		"ቡናዬ"
	],
	"ወተት": [
		"ወተት",
		"ወተትን",
		"ወተትው",
		"ወተትያቸው",
		"ወተትዬ"
	],
	"እንቁላል": [
		"እንቁላል",
		"እንቁላልን",
		"እንቁላልው",
		"እንቁላልያቸው",
		"እንቁላልዬ"
	],
	"ምሳ": [
		"ምሳ",
		"ምሳን",
		"ምሳው",
		"ምሳያቸው",
		"ምሳዬ"
	],
	"ቁርስ": [
		"ቁርስ",
		"ቁርስን",
		"ቁርስው",
		"ቁርስያቸው",
		"ቁርስዬ"
	],
	"እራት": [
		"እራት",
		"እራትን",
		"እራትው",
		"እራትያቸው",
		"እራትዬ"
	],
	"ስኳር": [
		"ስኳር",
		"ስኳርን",
		"ስኳርው",
		"ስኳርያቸው",
		"ስኳርዬ"
	],
	"ጨው": [
		"ጨው",
		"ጨውን",
		"ጨውው",
		"ጨውያቸው",
		"ጨውዬ"
	],
	"ቅመም": [
		"ቅመም",
		"ቅመምን",
		"ቅመምው",
		"ቅመምያቸው",
		"ቅመምዬ"
	],
	"ዘይት": [
		"ዘይት",
		"ዘይትን",
		"ዘይትው",
		"ዘይትያቸው",
		"ዘይትዬ"
	],
	"ስንዴ": [
		"ስንዴ",
		"ስንዴን",
		"ስንዴው",
		"ስንዴያቸው",
		"ስንዴዬ"
	],
	"በቆሎ": [
		"በቆሎ",
		"በቆሎን",
		"በቆሎው",
		"በቆሎያቸው",
		"በቆሎዬ"
	],
	"ሩዝ": [
		"ሩዝ",
		"ሩዝን",
		"ሩዝው",
		"ሩዝያቸው",
		"ሩዝዬ"
	],
	"ፍራፍሬ": [
		"ፍራፍሬ",
		"ፍራፍሬን",
		"ፍራፍሬው",
		"ፍራፍሬያቸው",
		"ፍራፍሬዬ"
	],
	"ቤርቤር": [
		"ቤርቤር",
		"ቤርቤርን",
		"ቤርቤርው",
		"ቤርቤርያቸው",
		"ቤርቤርዬ"
	],
	"ቢራ": [
		"ቢራ",
		"ቢራን",
		"ቢራው",
		"ቢራያቸው",
		"ቢራዬ"
	],
	"ውሃ": [
		"ውሃ",
		"ውሃን",
		"ውሃው",
		"ውሃያቸው",
		"ውሃዬ"
	],
	"አየር": [
		"አየር",
		"አየርን",
		"አየርው",
		"አየርያቸው",
		"አየርዬ"
	],
	"መሬት": [
		"መሬት",
		"መሬትን",
		"መሬትው",
		"መሬትያቸው",
		"መሬትዬ"
	],
	"ከተማ": [
		"ከተማ",
		"ከተማን",
		"ከተማው",
		"ከተማያቸው",
		"ከተማዬ"
	],
	"መንደር": [
		"መንደር",
		"መንደርን",
		"መንደርው",
		"መንደርያቸው",
		"መንደርዬ"
	],
	"ገጠር": [
		"ገጠር",
		"ገጠርን",
		"ገጠርው",
		"ገጠርያቸው",
		"ገጠርዬ"
	],
	"ቤተሰብ": [
		"ቤተሰብ",
		"ቤተሰብን",
		"ቤተሰብው",
		"ቤተሰብያቸው",
		"ቤተሰብዬ"
	],
	"እናት": [
		"እናት",
		"እናትን",
		"እናትው",
		"እናትያቸው",
		"እናትዬ"
	],
	"አባት": [
		"አባት",
		"አባትን",
		"አባትው",
		"አባትያቸው",
		"አባትዬ"
	],
	"ልጅ": [
		"ልጅ",
		"ልጅን",
		"ልጅው",
		"ልጅያቸው",
		"ልጅዬ"
	],
	"ወንድም": [
		"ወንድም",
		"ወንድምን",
		"ወንድምው",
		"ወንድምያቸው",
		"ወንድምዬ"
	],
	"እህት": [
		"እህት",
		"እህትን",
		"እህትው",
		"እህትያቸው",
		"እህትዬ"
	],
	"ባል": [
		"ባል",
		"ባልን",
		"ባልው",
		"ባልያቸው",
		"ባልዬ"
	],
	"ሚስት": [
		"ሚስት",
		"ሚስትን",
		"ሚስትው",
		"ሚስትያቸው",
		"ሚስትዬ"
	],
	"ወዳጅ": [
		"ወዳጅ",
		"ወዳጅን",
		"ወዳጅው",
		"ወዳጅያቸው",
		"ወዳጅዬ"
	],
	"አያት": [
		"አያት",
		"አያትን",
		"አያትው",
		"አያትያቸው",
		"አያትዬ"
	],
	"አያያት": [
		"አያያት",
		"አያያትን",
		"አያያትው",
		"አያያትያቸው",
		"አያያትዬ"
	],
	"አጎት": [
		"አጎት",
		"አጎትን",
		"አጎትው",
		"አጎትያቸው",
		"አጎትዬ"
	],
	"ወንድ": [
		"ወንድ",
		"ወንድን",
		"ወንድው",
		"ወንድያቸው",
		"ወንድዬ"
	],
	"ሴት": [
		"ሴት",
		"ሴትን",
		"ሴትው",
		"ሴትያቸው",
		"ሴትዬ"
	],
	"ጊዜ": [
		"ጊዜ",
		"ጊዜን",
		"ጊዜው",
		"ጊዜያቸው",
		"ጊዜዬ"
	],
	"ሰዓት": [
		"ሰዓት",
		"ሰዓትን",
		"ሰዓትው",
		"ሰዓትያቸው",
		"ሰዓትዬ"
	],
	"ደቂቃ": [
		"ደቂቃ",
		"ደቂቃን",
		"ደቂቃው",
		"ደቂቃያቸው",
		"ደቂቃዬ"
	]
}
